.coveragerc
.gitignore
.travis.yml
LICENSE
README.md
manage.py
setup.cfg
setup.py
django_gpxpy/__init__.py
django_gpxpy/gpx_parse.py
django_gpxpy.egg-info/PKG-INFO
django_gpxpy.egg-info/SOURCES.txt
django_gpxpy.egg-info/dependency_links.txt
django_gpxpy.egg-info/requires.txt
django_gpxpy.egg-info/top_level.txt
tests/__init__.py
tests/settings.py
tests/test.py
tests/test_data/test_bad_file.gpx
tests/test_data/test_track.gpx
tests/test_data/test_track.gpx.gz
tests/test_data/test_with_route.gpx