Metadata-Version: 1.1
Name: django-gpxpy
Version: 0.0.2
Summary: Django integration of GpxPy
Home-page: https://github.com/PetrDlouhy/django-gpxpy
Author: Petr Dlouhý <petr.dlouhy@email.cz>
Author-email: petr.dlouhy@email.cz
License: UNKNOWN
Download-URL: https://github.com/PetrDlouhy/django-gpxpy/archive/master.zip
Platform: UNKNOWN
Classifier: Development Status :: 4 - Beta
Classifier: Framework :: Django
Classifier: Intended Audience :: Developers
Classifier: Intended Audience :: System Administrators
Classifier: Intended Audience :: System Administrators
Classifier: Operating System :: OS Independent
Classifier: Topic :: Software Development
Classifier: Programming Language :: Python :: 2.7
Classifier: Programming Language :: Python :: 3.4
Classifier: Programming Language :: Python :: 3.5
Classifier: Framework :: Django :: 1.8
Classifier: Framework :: Django :: 1.9
Classifier: Framework :: Django :: 1.10
